{
  "event_id": "hyrox-tenerife-2026",
  "event_name": "HYROX Tenerife",
  "url": "https://spain.hyrox.com/checkout/hyrox-tenerife-season-26-27-iv1ecx",
  "history": [
    {
      "date": "2026-03-21",
      "fetched_at": "2026-03-21T19:25:45.750942+01:00",
      "total_stock": 18,
      "data": {
        "tickets": [
          {
            "parkur": "Singles",
            "ticket": "HYROX MEN | Saturday",
            "stock": 94
          },
          {
            "parkur": "Singles",
            "ticket": "HYROX PRO MEN | Saturday",
            "stock": 146
          },
          {
            "parkur": "Singles",
            "ticket": "HYROX PRO WOMEN | Saturday",
            "stock": 30
          },
          {
            "parkur": "Singles",
            "ticket": "CHARITY | HYROX MEN | Saturday",
            "stock": 48
          },
          {
            "parkur": "Singles",
            "ticket": "CHARITY | HYROX PRO WOMEN | Saturday",
            "stock": 30
          },
          {
            "parkur": "Singles",
            "ticket": "CHARITY | HYROX PRO MEN | Saturday",
            "stock": 30
          },
          {
            "parkur": "Singles",
            "ticket": "HYROX ADAPTIVE MEN | Saturday",
            "stock": 7
          },
          {
            "parkur": "Singles",
            "ticket": "HYROX WOMEN | Sunday",
            "stock": 81
          },
          {
            "parkur": "Singles",
            "ticket": "CHARITY | HYROX WOMEN | Sunday",
            "stock": 48
          },
          {
            "parkur": "Singles",
            "ticket": "HYROX ADAPTIVE WOMEN | Sunday",
            "stock": 7
          },
          {
            "parkur": "Doubles",
            "ticket": "HYROX PRO DOUBLES MEN | Saturday",
            "stock": 60
          },
          {
            "parkur": "Doubles",
            "ticket": "CHARITY | HYROX DOUBLES MIXED | Saturday",
            "stock": 26
          },
          {
            "parkur": "Doubles",
            "ticket": "CHARITY | HYROX PRO DOUBLES WOMEN | Saturday",
            "stock": 30
          },
          {
            "parkur": "Doubles",
            "ticket": "CHARITY | HYROX PRO DOUBLES MEN | Saturday",
            "stock": 30
          },
          {
            "parkur": "Doubles",
            "ticket": "CHARITY | HYROX PRO DOUBLES MEN ATHLETE 2 | Saturday",
            "stock": 30
          },
          {
            "parkur": "Doubles",
            "ticket": "HYROX DOUBLES MEN | Sunday",
            "stock": 334
          },
          {
            "parkur": "Doubles",
            "ticket": "CHARITY | HYROX DOUBLES MEN | Sunday",
            "stock": 26
          },
          {
            "parkur": "Doubles",
            "ticket": "CHARITY | HYROX DOUBLES WOMEN | Sunday",
            "stock": 26
          }
        ],
        "by_parkur": {
          "Singles": {
            "HYROX MEN | Saturday": 94,
            "HYROX PRO MEN | Saturday": 146,
            "HYROX PRO WOMEN | Saturday": 30,
            "CHARITY | HYROX MEN | Saturday": 48,
            "CHARITY | HYROX PRO WOMEN | Saturday": 30,
            "CHARITY | HYROX PRO MEN | Saturday": 30,
            "HYROX ADAPTIVE MEN | Saturday": 7,
            "HYROX WOMEN | Sunday": 81,
            "CHARITY | HYROX WOMEN | Sunday": 48,
            "HYROX ADAPTIVE WOMEN | Sunday": 7
          },
          "Doubles": {
            "HYROX PRO DOUBLES MEN | Saturday": 60,
            "CHARITY | HYROX DOUBLES MIXED | Saturday": 26,
            "CHARITY | HYROX PRO DOUBLES WOMEN | Saturday": 30,
            "CHARITY | HYROX PRO DOUBLES MEN | Saturday": 30,
            "CHARITY | HYROX PRO DOUBLES MEN ATHLETE 2 | Saturday": 30,
            "HYROX DOUBLES MEN | Sunday": 334,
            "CHARITY | HYROX DOUBLES MEN | Sunday": 26,
            "CHARITY | HYROX DOUBLES WOMEN | Sunday": 26
          }
        }
      }
    },
    {
      "date": "2026-03-22",
      "fetched_at": "2026-03-22T19:26:10.522563+01:00",
      "total_stock": 18,
      "data": {
        "tickets": [
          {
            "parkur": "Singles",
            "ticket": "HYROX MEN | Saturday",
            "stock": 74
          },
          {
            "parkur": "Singles",
            "ticket": "HYROX PRO MEN | Saturday",
            "stock": 142
          },
          {
            "parkur": "Singles",
            "ticket": "HYROX PRO WOMEN | Saturday",
            "stock": 29
          },
          {
            "parkur": "Singles",
            "ticket": "CHARITY | HYROX MEN | Saturday",
            "stock": 48
          },
          {
            "parkur": "Singles",
            "ticket": "CHARITY | HYROX PRO WOMEN | Saturday",
            "stock": 30
          },
          {
            "parkur": "Singles",
            "ticket": "CHARITY | HYROX PRO MEN | Saturday",
            "stock": 30
          },
          {
            "parkur": "Singles",
            "ticket": "HYROX ADAPTIVE MEN | Saturday",
            "stock": 7
          },
          {
            "parkur": "Singles",
            "ticket": "HYROX WOMEN | Sunday",
            "stock": 70
          },
          {
            "parkur": "Singles",
            "ticket": "CHARITY | HYROX WOMEN | Sunday",
            "stock": 48
          },
          {
            "parkur": "Singles",
            "ticket": "HYROX ADAPTIVE WOMEN | Sunday",
            "stock": 7
          },
          {
            "parkur": "Doubles",
            "ticket": "HYROX PRO DOUBLES MEN | Saturday",
            "stock": 58
          },
          {
            "parkur": "Doubles",
            "ticket": "CHARITY | HYROX DOUBLES MIXED | Saturday",
            "stock": 22
          },
          {
            "parkur": "Doubles",
            "ticket": "CHARITY | HYROX PRO DOUBLES WOMEN | Saturday",
            "stock": 30
          },
          {
            "parkur": "Doubles",
            "ticket": "CHARITY | HYROX PRO DOUBLES MEN | Saturday",
            "stock": 30
          },
          {
            "parkur": "Doubles",
            "ticket": "CHARITY | HYROX PRO DOUBLES MEN ATHLETE 2 | Saturday",
            "stock": 30
          },
          {
            "parkur": "Doubles",
            "ticket": "HYROX DOUBLES MEN | Sunday",
            "stock": 320
          },
          {
            "parkur": "Doubles",
            "ticket": "CHARITY | HYROX DOUBLES MEN | Sunday",
            "stock": 26
          },
          {
            "parkur": "Doubles",
            "ticket": "CHARITY | HYROX DOUBLES WOMEN | Sunday",
            "stock": 25
          }
        ],
        "by_parkur": {
          "Singles": {
            "HYROX MEN | Saturday": 74,
            "HYROX PRO MEN | Saturday": 142,
            "HYROX PRO WOMEN | Saturday": 29,
            "CHARITY | HYROX MEN | Saturday": 48,
            "CHARITY | HYROX PRO WOMEN | Saturday": 30,
            "CHARITY | HYROX PRO MEN | Saturday": 30,
            "HYROX ADAPTIVE MEN | Saturday": 7,
            "HYROX WOMEN | Sunday": 70,
            "CHARITY | HYROX WOMEN | Sunday": 48,
            "HYROX ADAPTIVE WOMEN | Sunday": 7
          },
          "Doubles": {
            "HYROX PRO DOUBLES MEN | Saturday": 58,
            "CHARITY | HYROX DOUBLES MIXED | Saturday": 22,
            "CHARITY | HYROX PRO DOUBLES WOMEN | Saturday": 30,
            "CHARITY | HYROX PRO DOUBLES MEN | Saturday": 30,
            "CHARITY | HYROX PRO DOUBLES MEN ATHLETE 2 | Saturday": 30,
            "HYROX DOUBLES MEN | Sunday": 320,
            "CHARITY | HYROX DOUBLES MEN | Sunday": 26,
            "CHARITY | HYROX DOUBLES WOMEN | Sunday": 25
          }
        }
      }
    },
    {
      "date": "2026-03-23",
      "fetched_at": "2026-03-23T19:41:08.402155+01:00",
      "total_stock": 18,
      "data": {
        "tickets": [
          {
            "parkur": "Singles",
            "ticket": "HYROX MEN | Saturday",
            "stock": 46
          },
          {
            "parkur": "Singles",
            "ticket": "HYROX PRO MEN | Saturday",
            "stock": 135
          },
          {
            "parkur": "Singles",
            "ticket": "HYROX PRO WOMEN | Saturday",
            "stock": 27
          },
          {
            "parkur": "Singles",
            "ticket": "CHARITY | HYROX MEN | Saturday",
            "stock": 47
          },
          {
            "parkur": "Singles",
            "ticket": "CHARITY | HYROX PRO WOMEN | Saturday",
            "stock": 30
          },
          {
            "parkur": "Singles",
            "ticket": "CHARITY | HYROX PRO MEN | Saturday",
            "stock": 30
          },
          {
            "parkur": "Singles",
            "ticket": "HYROX ADAPTIVE MEN | Saturday",
            "stock": 7
          },
          {
            "parkur": "Singles",
            "ticket": "HYROX WOMEN | Sunday",
            "stock": 52
          },
          {
            "parkur": "Singles",
            "ticket": "CHARITY | HYROX WOMEN | Sunday",
            "stock": 48
          },
          {
            "parkur": "Singles",
            "ticket": "HYROX ADAPTIVE WOMEN | Sunday",
            "stock": 7
          },
          {
            "parkur": "Doubles",
            "ticket": "HYROX PRO DOUBLES MEN | Saturday",
            "stock": 56
          },
          {
            "parkur": "Doubles",
            "ticket": "CHARITY | HYROX DOUBLES MIXED | Saturday",
            "stock": 22
          },
          {
            "parkur": "Doubles",
            "ticket": "CHARITY | HYROX PRO DOUBLES WOMEN | Saturday",
            "stock": 30
          },
          {
            "parkur": "Doubles",
            "ticket": "CHARITY | HYROX PRO DOUBLES MEN | Saturday",
            "stock": 30
          },
          {
            "parkur": "Doubles",
            "ticket": "CHARITY | HYROX PRO DOUBLES MEN ATHLETE 2 | Saturday",
            "stock": 30
          },
          {
            "parkur": "Doubles",
            "ticket": "HYROX DOUBLES MEN | Sunday",
            "stock": 310
          },
          {
            "parkur": "Doubles",
            "ticket": "CHARITY | HYROX DOUBLES MEN | Sunday",
            "stock": 26
          },
          {
            "parkur": "Doubles",
            "ticket": "CHARITY | HYROX DOUBLES WOMEN | Sunday",
            "stock": 25
          }
        ],
        "by_parkur": {
          "Singles": {
            "HYROX MEN | Saturday": 46,
            "HYROX PRO MEN | Saturday": 135,
            "HYROX PRO WOMEN | Saturday": 27,
            "CHARITY | HYROX MEN | Saturday": 47,
            "CHARITY | HYROX PRO WOMEN | Saturday": 30,
            "CHARITY | HYROX PRO MEN | Saturday": 30,
            "HYROX ADAPTIVE MEN | Saturday": 7,
            "HYROX WOMEN | Sunday": 52,
            "CHARITY | HYROX WOMEN | Sunday": 48,
            "HYROX ADAPTIVE WOMEN | Sunday": 7
          },
          "Doubles": {
            "HYROX PRO DOUBLES MEN | Saturday": 56,
            "CHARITY | HYROX DOUBLES MIXED | Saturday": 22,
            "CHARITY | HYROX PRO DOUBLES WOMEN | Saturday": 30,
            "CHARITY | HYROX PRO DOUBLES MEN | Saturday": 30,
            "CHARITY | HYROX PRO DOUBLES MEN ATHLETE 2 | Saturday": 30,
            "HYROX DOUBLES MEN | Sunday": 310,
            "CHARITY | HYROX DOUBLES MEN | Sunday": 26,
            "CHARITY | HYROX DOUBLES WOMEN | Sunday": 25
          }
        }
      }
    },
    {
      "date": "2026-03-24",
      "fetched_at": "2026-03-24T19:52:01.126022+01:00",
      "total_stock": 18,
      "data": {
        "tickets": [
          {
            "parkur": "Singles",
            "ticket": "HYROX MEN | Saturday",
            "stock": 18
          },
          {
            "parkur": "Singles",
            "ticket": "HYROX PRO MEN | Saturday",
            "stock": 125
          },
          {
            "parkur": "Singles",
            "ticket": "HYROX PRO WOMEN | Saturday",
            "stock": 25
          },
          {
            "parkur": "Singles",
            "ticket": "CHARITY | HYROX MEN | Saturday",
            "stock": 47
          },
          {
            "parkur": "Singles",
            "ticket": "CHARITY | HYROX PRO WOMEN | Saturday",
            "stock": 30
          },
          {
            "parkur": "Singles",
            "ticket": "CHARITY | HYROX PRO MEN | Saturday",
            "stock": 30
          },
          {
            "parkur": "Singles",
            "ticket": "HYROX ADAPTIVE MEN | Saturday",
            "stock": 7
          },
          {
            "parkur": "Singles",
            "ticket": "HYROX WOMEN | Sunday",
            "stock": 40
          },
          {
            "parkur": "Singles",
            "ticket": "CHARITY | HYROX WOMEN | Sunday",
            "stock": 48
          },
          {
            "parkur": "Singles",
            "ticket": "HYROX ADAPTIVE WOMEN | Sunday",
            "stock": 7
          },
          {
            "parkur": "Doubles",
            "ticket": "HYROX PRO DOUBLES MEN | Saturday",
            "stock": 53
          },
          {
            "parkur": "Doubles",
            "ticket": "CHARITY | HYROX DOUBLES MIXED | Saturday",
            "stock": 20
          },
          {
            "parkur": "Doubles",
            "ticket": "CHARITY | HYROX PRO DOUBLES WOMEN | Saturday",
            "stock": 30
          },
          {
            "parkur": "Doubles",
            "ticket": "CHARITY | HYROX PRO DOUBLES MEN | Saturday",
            "stock": 30
          },
          {
            "parkur": "Doubles",
            "ticket": "CHARITY | HYROX PRO DOUBLES MEN ATHLETE 2 | Saturday",
            "stock": 30
          },
          {
            "parkur": "Doubles",
            "ticket": "HYROX DOUBLES MEN | Sunday",
            "stock": 301
          },
          {
            "parkur": "Doubles",
            "ticket": "CHARITY | HYROX DOUBLES MEN | Sunday",
            "stock": 26
          },
          {
            "parkur": "Doubles",
            "ticket": "CHARITY | HYROX DOUBLES WOMEN | Sunday",
            "stock": 23
          }
        ],
        "by_parkur": {
          "Singles": {
            "HYROX MEN | Saturday": 18,
            "HYROX PRO MEN | Saturday": 125,
            "HYROX PRO WOMEN | Saturday": 25,
            "CHARITY | HYROX MEN | Saturday": 47,
            "CHARITY | HYROX PRO WOMEN | Saturday": 30,
            "CHARITY | HYROX PRO MEN | Saturday": 30,
            "HYROX ADAPTIVE MEN | Saturday": 7,
            "HYROX WOMEN | Sunday": 40,
            "CHARITY | HYROX WOMEN | Sunday": 48,
            "HYROX ADAPTIVE WOMEN | Sunday": 7
          },
          "Doubles": {
            "HYROX PRO DOUBLES MEN | Saturday": 53,
            "CHARITY | HYROX DOUBLES MIXED | Saturday": 20,
            "CHARITY | HYROX PRO DOUBLES WOMEN | Saturday": 30,
            "CHARITY | HYROX PRO DOUBLES MEN | Saturday": 30,
            "CHARITY | HYROX PRO DOUBLES MEN ATHLETE 2 | Saturday": 30,
            "HYROX DOUBLES MEN | Sunday": 301,
            "CHARITY | HYROX DOUBLES MEN | Sunday": 26,
            "CHARITY | HYROX DOUBLES WOMEN | Sunday": 23
          }
        }
      }
    },
    {
      "date": "2026-03-25",
      "fetched_at": "2026-03-25T19:45:10.407845+01:00",
      "total_stock": 17,
      "data": {
        "tickets": [
          {
            "parkur": "Singles",
            "ticket": "HYROX PRO MEN | Saturday",
            "stock": 103
          },
          {
            "parkur": "Singles",
            "ticket": "HYROX PRO WOMEN | Saturday",
            "stock": 20
          },
          {
            "parkur": "Singles",
            "ticket": "CHARITY | HYROX MEN | Saturday",
            "stock": 47
          },
          {
            "parkur": "Singles",
            "ticket": "CHARITY | HYROX PRO WOMEN | Saturday",
            "stock": 30
          },
          {
            "parkur": "Singles",
            "ticket": "CHARITY | HYROX PRO MEN | Saturday",
            "stock": 30
          },
          {
            "parkur": "Singles",
            "ticket": "HYROX ADAPTIVE MEN | Saturday",
            "stock": 7
          },
          {
            "parkur": "Singles",
            "ticket": "HYROX WOMEN | Sunday",
            "stock": 27
          },
          {
            "parkur": "Singles",
            "ticket": "CHARITY | HYROX WOMEN | Sunday",
            "stock": 48
          },
          {
            "parkur": "Singles",
            "ticket": "HYROX ADAPTIVE WOMEN | Sunday",
            "stock": 7
          },
          {
            "parkur": "Doubles",
            "ticket": "HYROX PRO DOUBLES MEN | Saturday",
            "stock": 52
          },
          {
            "parkur": "Doubles",
            "ticket": "CHARITY | HYROX DOUBLES MIXED | Saturday",
            "stock": 19
          },
          {
            "parkur": "Doubles",
            "ticket": "CHARITY | HYROX PRO DOUBLES WOMEN | Saturday",
            "stock": 29
          },
          {
            "parkur": "Doubles",
            "ticket": "CHARITY | HYROX PRO DOUBLES MEN | Saturday",
            "stock": 30
          },
          {
            "parkur": "Doubles",
            "ticket": "CHARITY | HYROX PRO DOUBLES MEN ATHLETE 2 | Saturday",
            "stock": 30
          },
          {
            "parkur": "Doubles",
            "ticket": "HYROX DOUBLES MEN | Sunday",
            "stock": 290
          },
          {
            "parkur": "Doubles",
            "ticket": "CHARITY | HYROX DOUBLES MEN | Sunday",
            "stock": 26
          },
          {
            "parkur": "Doubles",
            "ticket": "CHARITY | HYROX DOUBLES WOMEN | Sunday",
            "stock": 23
          }
        ],
        "by_parkur": {
          "Singles": {
            "HYROX PRO MEN | Saturday": 103,
            "HYROX PRO WOMEN | Saturday": 20,
            "CHARITY | HYROX MEN | Saturday": 47,
            "CHARITY | HYROX PRO WOMEN | Saturday": 30,
            "CHARITY | HYROX PRO MEN | Saturday": 30,
            "HYROX ADAPTIVE MEN | Saturday": 7,
            "HYROX WOMEN | Sunday": 27,
            "CHARITY | HYROX WOMEN | Sunday": 48,
            "HYROX ADAPTIVE WOMEN | Sunday": 7
          },
          "Doubles": {
            "HYROX PRO DOUBLES MEN | Saturday": 52,
            "CHARITY | HYROX DOUBLES MIXED | Saturday": 19,
            "CHARITY | HYROX PRO DOUBLES WOMEN | Saturday": 29,
            "CHARITY | HYROX PRO DOUBLES MEN | Saturday": 30,
            "CHARITY | HYROX PRO DOUBLES MEN ATHLETE 2 | Saturday": 30,
            "HYROX DOUBLES MEN | Sunday": 290,
            "CHARITY | HYROX DOUBLES MEN | Sunday": 26,
            "CHARITY | HYROX DOUBLES WOMEN | Sunday": 23
          }
        }
      }
    },
    {
      "date": "2026-03-26",
      "fetched_at": "2026-03-26T19:55:37.691501+01:00",
      "total_stock": 19,
      "data": {
        "tickets": [
          {
            "parkur": "Singles",
            "ticket": "HYROX PRO MEN | Saturday",
            "stock": 91
          },
          {
            "parkur": "Singles",
            "ticket": "HYROX PRO WOMEN | Saturday",
            "stock": 19
          },
          {
            "parkur": "Singles",
            "ticket": "CHARITY | HYROX MEN | Saturday",
            "stock": 47
          },
          {
            "parkur": "Singles",
            "ticket": "CHARITY | HYROX PRO WOMEN | Saturday",
            "stock": 30
          },
          {
            "parkur": "Singles",
            "ticket": "CHARITY | HYROX PRO MEN | Saturday",
            "stock": 30
          },
          {
            "parkur": "Singles",
            "ticket": "HYROX ADAPTIVE MEN | Saturday",
            "stock": 5
          },
          {
            "parkur": "Singles",
            "ticket": "HYROX WOMEN | Sunday",
            "stock": 17
          },
          {
            "parkur": "Singles",
            "ticket": "CHARITY | HYROX WOMEN | Sunday",
            "stock": 48
          },
          {
            "parkur": "Singles",
            "ticket": "HYROX ADAPTIVE WOMEN | Sunday",
            "stock": 7
          },
          {
            "parkur": "Doubles",
            "ticket": "HYROX DOUBLES MIXED | Saturday",
            "stock": 16
          },
          {
            "parkur": "Doubles",
            "ticket": "HYROX PRO DOUBLES MEN | Saturday",
            "stock": 50
          },
          {
            "parkur": "Doubles",
            "ticket": "CHARITY | HYROX DOUBLES MIXED | Saturday",
            "stock": 19
          },
          {
            "parkur": "Doubles",
            "ticket": "CHARITY | HYROX PRO DOUBLES WOMEN | Saturday",
            "stock": 29
          },
          {
            "parkur": "Doubles",
            "ticket": "CHARITY | HYROX PRO DOUBLES MEN | Saturday",
            "stock": 30
          },
          {
            "parkur": "Doubles",
            "ticket": "CHARITY | HYROX PRO DOUBLES MEN ATHLETE 2 | Saturday",
            "stock": 30
          },
          {
            "parkur": "Doubles",
            "ticket": "HYROX DOUBLES MEN | Sunday",
            "stock": 185
          },
          {
            "parkur": "Doubles",
            "ticket": "HYROX DOUBLES WOMEN | Sunday",
            "stock": 56
          },
          {
            "parkur": "Doubles",
            "ticket": "CHARITY | HYROX DOUBLES MEN | Sunday",
            "stock": 25
          },
          {
            "parkur": "Doubles",
            "ticket": "CHARITY | HYROX DOUBLES WOMEN | Sunday",
            "stock": 21
          }
        ],
        "by_parkur": {
          "Singles": {
            "HYROX PRO MEN | Saturday": 91,
            "HYROX PRO WOMEN | Saturday": 19,
            "CHARITY | HYROX MEN | Saturday": 47,
            "CHARITY | HYROX PRO WOMEN | Saturday": 30,
            "CHARITY | HYROX PRO MEN | Saturday": 30,
            "HYROX ADAPTIVE MEN | Saturday": 5,
            "HYROX WOMEN | Sunday": 17,
            "CHARITY | HYROX WOMEN | Sunday": 48,
            "HYROX ADAPTIVE WOMEN | Sunday": 7
          },
          "Doubles": {
            "HYROX DOUBLES MIXED | Saturday": 16,
            "HYROX PRO DOUBLES MEN | Saturday": 50,
            "CHARITY | HYROX DOUBLES MIXED | Saturday": 19,
            "CHARITY | HYROX PRO DOUBLES WOMEN | Saturday": 29,
            "CHARITY | HYROX PRO DOUBLES MEN | Saturday": 30,
            "CHARITY | HYROX PRO DOUBLES MEN ATHLETE 2 | Saturday": 30,
            "HYROX DOUBLES MEN | Sunday": 185,
            "HYROX DOUBLES WOMEN | Sunday": 56,
            "CHARITY | HYROX DOUBLES MEN | Sunday": 25,
            "CHARITY | HYROX DOUBLES WOMEN | Sunday": 21
          }
        }
      }
    },
    {
      "date": "2026-03-27",
      "fetched_at": "2026-03-27T19:45:08.043048+01:00",
      "total_stock": 18,
      "data": {
        "tickets": [
          {
            "parkur": "Singles",
            "ticket": "HYROX PRO MEN | Saturday",
            "stock": 80
          },
          {
            "parkur": "Singles",
            "ticket": "HYROX PRO WOMEN | Saturday",
            "stock": 13
          },
          {
            "parkur": "Singles",
            "ticket": "CHARITY | HYROX MEN | Saturday",
            "stock": 45
          },
          {
            "parkur": "Singles",
            "ticket": "CHARITY | HYROX PRO WOMEN | Saturday",
            "stock": 30
          },
          {
            "parkur": "Singles",
            "ticket": "CHARITY | HYROX PRO MEN | Saturday",
            "stock": 30
          },
          {
            "parkur": "Singles",
            "ticket": "HYROX ADAPTIVE MEN | Saturday",
            "stock": 5
          },
          {
            "parkur": "Singles",
            "ticket": "HYROX WOMEN | Sunday",
            "stock": 7
          },
          {
            "parkur": "Singles",
            "ticket": "CHARITY | HYROX WOMEN | Sunday",
            "stock": 48
          },
          {
            "parkur": "Singles",
            "ticket": "HYROX ADAPTIVE WOMEN | Sunday",
            "stock": 7
          },
          {
            "parkur": "Doubles",
            "ticket": "HYROX PRO DOUBLES MEN | Saturday",
            "stock": 49
          },
          {
            "parkur": "Doubles",
            "ticket": "CHARITY | HYROX DOUBLES MIXED | Saturday",
            "stock": 20
          },
          {
            "parkur": "Doubles",
            "ticket": "CHARITY | HYROX PRO DOUBLES WOMEN | Saturday",
            "stock": 28
          },
          {
            "parkur": "Doubles",
            "ticket": "CHARITY | HYROX PRO DOUBLES MEN | Saturday",
            "stock": 30
          },
          {
            "parkur": "Doubles",
            "ticket": "CHARITY | HYROX PRO DOUBLES MEN ATHLETE 2 | Saturday",
            "stock": 30
          },
          {
            "parkur": "Doubles",
            "ticket": "HYROX DOUBLES MEN | Sunday",
            "stock": 178
          },
          {
            "parkur": "Doubles",
            "ticket": "HYROX DOUBLES WOMEN | Sunday",
            "stock": 40
          },
          {
            "parkur": "Doubles",
            "ticket": "CHARITY | HYROX DOUBLES MEN | Sunday",
            "stock": 25
          },
          {
            "parkur": "Doubles",
            "ticket": "CHARITY | HYROX DOUBLES WOMEN | Sunday",
            "stock": 21
          }
        ],
        "by_parkur": {
          "Singles": {
            "HYROX PRO MEN | Saturday": 80,
            "HYROX PRO WOMEN | Saturday": 13,
            "CHARITY | HYROX MEN | Saturday": 45,
            "CHARITY | HYROX PRO WOMEN | Saturday": 30,
            "CHARITY | HYROX PRO MEN | Saturday": 30,
            "HYROX ADAPTIVE MEN | Saturday": 5,
            "HYROX WOMEN | Sunday": 7,
            "CHARITY | HYROX WOMEN | Sunday": 48,
            "HYROX ADAPTIVE WOMEN | Sunday": 7
          },
          "Doubles": {
            "HYROX PRO DOUBLES MEN | Saturday": 49,
            "CHARITY | HYROX DOUBLES MIXED | Saturday": 20,
            "CHARITY | HYROX PRO DOUBLES WOMEN | Saturday": 28,
            "CHARITY | HYROX PRO DOUBLES MEN | Saturday": 30,
            "CHARITY | HYROX PRO DOUBLES MEN ATHLETE 2 | Saturday": 30,
            "HYROX DOUBLES MEN | Sunday": 178,
            "HYROX DOUBLES WOMEN | Sunday": 40,
            "CHARITY | HYROX DOUBLES MEN | Sunday": 25,
            "CHARITY | HYROX DOUBLES WOMEN | Sunday": 21
          }
        }
      }
    },
    {
      "date": "2026-03-28",
      "fetched_at": "2026-03-28T19:29:24.089260+01:00",
      "total_stock": 18,
      "data": {
        "tickets": [
          {
            "parkur": "Singles",
            "ticket": "HYROX PRO MEN | Saturday",
            "stock": 72
          },
          {
            "parkur": "Singles",
            "ticket": "HYROX PRO WOMEN | Saturday",
            "stock": 13
          },
          {
            "parkur": "Singles",
            "ticket": "CHARITY | HYROX MEN | Saturday",
            "stock": 44
          },
          {
            "parkur": "Singles",
            "ticket": "CHARITY | HYROX PRO WOMEN | Saturday",
            "stock": 30
          },
          {
            "parkur": "Singles",
            "ticket": "CHARITY | HYROX PRO MEN | Saturday",
            "stock": 29
          },
          {
            "parkur": "Singles",
            "ticket": "HYROX ADAPTIVE MEN | Saturday",
            "stock": 5
          },
          {
            "parkur": "Singles",
            "ticket": "HYROX WOMEN | Sunday",
            "stock": 3
          },
          {
            "parkur": "Singles",
            "ticket": "CHARITY | HYROX WOMEN | Sunday",
            "stock": 48
          },
          {
            "parkur": "Singles",
            "ticket": "HYROX ADAPTIVE WOMEN | Sunday",
            "stock": 7
          },
          {
            "parkur": "Doubles",
            "ticket": "HYROX PRO DOUBLES MEN | Saturday",
            "stock": 47
          },
          {
            "parkur": "Doubles",
            "ticket": "CHARITY | HYROX DOUBLES MIXED | Saturday",
            "stock": 19
          },
          {
            "parkur": "Doubles",
            "ticket": "CHARITY | HYROX PRO DOUBLES WOMEN | Saturday",
            "stock": 28
          },
          {
            "parkur": "Doubles",
            "ticket": "CHARITY | HYROX PRO DOUBLES MEN | Saturday",
            "stock": 30
          },
          {
            "parkur": "Doubles",
            "ticket": "CHARITY | HYROX PRO DOUBLES MEN ATHLETE 2 | Saturday",
            "stock": 30
          },
          {
            "parkur": "Doubles",
            "ticket": "HYROX DOUBLES MEN | Sunday",
            "stock": 167
          },
          {
            "parkur": "Doubles",
            "ticket": "HYROX DOUBLES WOMEN | Sunday",
            "stock": 27
          },
          {
            "parkur": "Doubles",
            "ticket": "CHARITY | HYROX DOUBLES MEN | Sunday",
            "stock": 25
          },
          {
            "parkur": "Doubles",
            "ticket": "CHARITY | HYROX DOUBLES WOMEN | Sunday",
            "stock": 21
          }
        ],
        "by_parkur": {
          "Singles": {
            "HYROX PRO MEN | Saturday": 72,
            "HYROX PRO WOMEN | Saturday": 13,
            "CHARITY | HYROX MEN | Saturday": 44,
            "CHARITY | HYROX PRO WOMEN | Saturday": 30,
            "CHARITY | HYROX PRO MEN | Saturday": 29,
            "HYROX ADAPTIVE MEN | Saturday": 5,
            "HYROX WOMEN | Sunday": 3,
            "CHARITY | HYROX WOMEN | Sunday": 48,
            "HYROX ADAPTIVE WOMEN | Sunday": 7
          },
          "Doubles": {
            "HYROX PRO DOUBLES MEN | Saturday": 47,
            "CHARITY | HYROX DOUBLES MIXED | Saturday": 19,
            "CHARITY | HYROX PRO DOUBLES WOMEN | Saturday": 28,
            "CHARITY | HYROX PRO DOUBLES MEN | Saturday": 30,
            "CHARITY | HYROX PRO DOUBLES MEN ATHLETE 2 | Saturday": 30,
            "HYROX DOUBLES MEN | Sunday": 167,
            "HYROX DOUBLES WOMEN | Sunday": 27,
            "CHARITY | HYROX DOUBLES MEN | Sunday": 25,
            "CHARITY | HYROX DOUBLES WOMEN | Sunday": 21
          }
        }
      }
    },
    {
      "date": "2026-03-29",
      "fetched_at": "2026-03-29T20:30:45.089383+02:00",
      "total_stock": 17,
      "data": {
        "tickets": [
          {
            "parkur": "Singles",
            "ticket": "HYROX PRO MEN | Saturday",
            "stock": 65
          },
          {
            "parkur": "Singles",
            "ticket": "HYROX PRO WOMEN | Saturday",
            "stock": 10
          },
          {
            "parkur": "Singles",
            "ticket": "CHARITY | HYROX MEN | Saturday",
            "stock": 41
          },
          {
            "parkur": "Singles",
            "ticket": "CHARITY | HYROX PRO WOMEN | Saturday",
            "stock": 30
          },
          {
            "parkur": "Singles",
            "ticket": "CHARITY | HYROX PRO MEN | Saturday",
            "stock": 29
          },
          {
            "parkur": "Singles",
            "ticket": "HYROX ADAPTIVE MEN | Saturday",
            "stock": 3
          },
          {
            "parkur": "Singles",
            "ticket": "CHARITY | HYROX WOMEN | Sunday",
            "stock": 47
          },
          {
            "parkur": "Singles",
            "ticket": "HYROX ADAPTIVE WOMEN | Sunday",
            "stock": 7
          },
          {
            "parkur": "Doubles",
            "ticket": "HYROX PRO DOUBLES MEN | Saturday",
            "stock": 40
          },
          {
            "parkur": "Doubles",
            "ticket": "CHARITY | HYROX DOUBLES MIXED | Saturday",
            "stock": 18
          },
          {
            "parkur": "Doubles",
            "ticket": "CHARITY | HYROX PRO DOUBLES WOMEN | Saturday",
            "stock": 28
          },
          {
            "parkur": "Doubles",
            "ticket": "CHARITY | HYROX PRO DOUBLES MEN | Saturday",
            "stock": 30
          },
          {
            "parkur": "Doubles",
            "ticket": "CHARITY | HYROX PRO DOUBLES MEN ATHLETE 2 | Saturday",
            "stock": 30
          },
          {
            "parkur": "Doubles",
            "ticket": "HYROX DOUBLES MEN | Sunday",
            "stock": 156
          },
          {
            "parkur": "Doubles",
            "ticket": "HYROX DOUBLES WOMEN | Sunday",
            "stock": 15
          },
          {
            "parkur": "Doubles",
            "ticket": "CHARITY | HYROX DOUBLES MEN | Sunday",
            "stock": 25
          },
          {
            "parkur": "Doubles",
            "ticket": "CHARITY | HYROX DOUBLES WOMEN | Sunday",
            "stock": 21
          }
        ],
        "by_parkur": {
          "Singles": {
            "HYROX PRO MEN | Saturday": 65,
            "HYROX PRO WOMEN | Saturday": 10,
            "CHARITY | HYROX MEN | Saturday": 41,
            "CHARITY | HYROX PRO WOMEN | Saturday": 30,
            "CHARITY | HYROX PRO MEN | Saturday": 29,
            "HYROX ADAPTIVE MEN | Saturday": 3,
            "CHARITY | HYROX WOMEN | Sunday": 47,
            "HYROX ADAPTIVE WOMEN | Sunday": 7
          },
          "Doubles": {
            "HYROX PRO DOUBLES MEN | Saturday": 40,
            "CHARITY | HYROX DOUBLES MIXED | Saturday": 18,
            "CHARITY | HYROX PRO DOUBLES WOMEN | Saturday": 28,
            "CHARITY | HYROX PRO DOUBLES MEN | Saturday": 30,
            "CHARITY | HYROX PRO DOUBLES MEN ATHLETE 2 | Saturday": 30,
            "HYROX DOUBLES MEN | Sunday": 156,
            "HYROX DOUBLES WOMEN | Sunday": 15,
            "CHARITY | HYROX DOUBLES MEN | Sunday": 25,
            "CHARITY | HYROX DOUBLES WOMEN | Sunday": 21
          }
        }
      }
    },
    {
      "date": "2026-03-30",
      "fetched_at": "2026-03-30T20:49:49.488416+02:00",
      "total_stock": 15,
      "data": {
        "tickets": [
          {
            "parkur": "Singles",
            "ticket": "HYROX PRO MEN | Saturday",
            "stock": 45
          },
          {
            "parkur": "Singles",
            "ticket": "CHARITY | HYROX MEN | Saturday",
            "stock": 39
          },
          {
            "parkur": "Singles",
            "ticket": "CHARITY | HYROX PRO WOMEN | Saturday",
            "stock": 30
          },
          {
            "parkur": "Singles",
            "ticket": "CHARITY | HYROX PRO MEN | Saturday",
            "stock": 29
          },
          {
            "parkur": "Singles",
            "ticket": "HYROX ADAPTIVE MEN | Saturday",
            "stock": 2
          },
          {
            "parkur": "Singles",
            "ticket": "CHARITY | HYROX WOMEN | Sunday",
            "stock": 46
          },
          {
            "parkur": "Singles",
            "ticket": "HYROX ADAPTIVE WOMEN | Sunday",
            "stock": 7
          },
          {
            "parkur": "Doubles",
            "ticket": "HYROX PRO DOUBLES MEN | Saturday",
            "stock": 37
          },
          {
            "parkur": "Doubles",
            "ticket": "CHARITY | HYROX DOUBLES MIXED | Saturday",
            "stock": 16
          },
          {
            "parkur": "Doubles",
            "ticket": "CHARITY | HYROX PRO DOUBLES WOMEN | Saturday",
            "stock": 28
          },
          {
            "parkur": "Doubles",
            "ticket": "CHARITY | HYROX PRO DOUBLES MEN | Saturday",
            "stock": 30
          },
          {
            "parkur": "Doubles",
            "ticket": "CHARITY | HYROX PRO DOUBLES MEN ATHLETE 2 | Saturday",
            "stock": 30
          },
          {
            "parkur": "Doubles",
            "ticket": "HYROX DOUBLES MEN | Sunday",
            "stock": 142
          },
          {
            "parkur": "Doubles",
            "ticket": "CHARITY | HYROX DOUBLES MEN | Sunday",
            "stock": 25
          },
          {
            "parkur": "Doubles",
            "ticket": "CHARITY | HYROX DOUBLES WOMEN | Sunday",
            "stock": 21
          }
        ],
        "by_parkur": {
          "Singles": {
            "HYROX PRO MEN | Saturday": 45,
            "CHARITY | HYROX MEN | Saturday": 39,
            "CHARITY | HYROX PRO WOMEN | Saturday": 30,
            "CHARITY | HYROX PRO MEN | Saturday": 29,
            "HYROX ADAPTIVE MEN | Saturday": 2,
            "CHARITY | HYROX WOMEN | Sunday": 46,
            "HYROX ADAPTIVE WOMEN | Sunday": 7
          },
          "Doubles": {
            "HYROX PRO DOUBLES MEN | Saturday": 37,
            "CHARITY | HYROX DOUBLES MIXED | Saturday": 16,
            "CHARITY | HYROX PRO DOUBLES WOMEN | Saturday": 28,
            "CHARITY | HYROX PRO DOUBLES MEN | Saturday": 30,
            "CHARITY | HYROX PRO DOUBLES MEN ATHLETE 2 | Saturday": 30,
            "HYROX DOUBLES MEN | Sunday": 142,
            "CHARITY | HYROX DOUBLES MEN | Sunday": 25,
            "CHARITY | HYROX DOUBLES WOMEN | Sunday": 21
          }
        }
      }
    },
    {
      "date": "2026-03-31",
      "fetched_at": "2026-03-31T20:51:00.007657+02:00",
      "total_stock": 15,
      "data": {
        "tickets": [
          {
            "parkur": "Singles",
            "ticket": "HYROX PRO MEN | Saturday",
            "stock": 29
          },
          {
            "parkur": "Singles",
            "ticket": "CHARITY | HYROX MEN | Saturday",
            "stock": 35
          },
          {
            "parkur": "Singles",
            "ticket": "CHARITY | HYROX PRO WOMEN | Saturday",
            "stock": 30
          },
          {
            "parkur": "Singles",
            "ticket": "CHARITY | HYROX PRO MEN | Saturday",
            "stock": 29
          },
          {
            "parkur": "Singles",
            "ticket": "HYROX ADAPTIVE MEN | Saturday",
            "stock": 2
          },
          {
            "parkur": "Singles",
            "ticket": "CHARITY | HYROX WOMEN | Sunday",
            "stock": 45
          },
          {
            "parkur": "Singles",
            "ticket": "HYROX ADAPTIVE WOMEN | Sunday",
            "stock": 7
          },
          {
            "parkur": "Doubles",
            "ticket": "HYROX PRO DOUBLES MEN | Saturday",
            "stock": 35
          },
          {
            "parkur": "Doubles",
            "ticket": "CHARITY | HYROX DOUBLES MIXED | Saturday",
            "stock": 12
          },
          {
            "parkur": "Doubles",
            "ticket": "CHARITY | HYROX PRO DOUBLES WOMEN | Saturday",
            "stock": 28
          },
          {
            "parkur": "Doubles",
            "ticket": "CHARITY | HYROX PRO DOUBLES MEN | Saturday",
            "stock": 30
          },
          {
            "parkur": "Doubles",
            "ticket": "CHARITY | HYROX PRO DOUBLES MEN ATHLETE 2 | Saturday",
            "stock": 30
          },
          {
            "parkur": "Doubles",
            "ticket": "HYROX DOUBLES MEN | Sunday",
            "stock": 134
          },
          {
            "parkur": "Doubles",
            "ticket": "CHARITY | HYROX DOUBLES MEN | Sunday",
            "stock": 25
          },
          {
            "parkur": "Doubles",
            "ticket": "CHARITY | HYROX DOUBLES WOMEN | Sunday",
            "stock": 20
          }
        ],
        "by_parkur": {
          "Singles": {
            "HYROX PRO MEN | Saturday": 29,
            "CHARITY | HYROX MEN | Saturday": 35,
            "CHARITY | HYROX PRO WOMEN | Saturday": 30,
            "CHARITY | HYROX PRO MEN | Saturday": 29,
            "HYROX ADAPTIVE MEN | Saturday": 2,
            "CHARITY | HYROX WOMEN | Sunday": 45,
            "HYROX ADAPTIVE WOMEN | Sunday": 7
          },
          "Doubles": {
            "HYROX PRO DOUBLES MEN | Saturday": 35,
            "CHARITY | HYROX DOUBLES MIXED | Saturday": 12,
            "CHARITY | HYROX PRO DOUBLES WOMEN | Saturday": 28,
            "CHARITY | HYROX PRO DOUBLES MEN | Saturday": 30,
            "CHARITY | HYROX PRO DOUBLES MEN ATHLETE 2 | Saturday": 30,
            "HYROX DOUBLES MEN | Sunday": 134,
            "CHARITY | HYROX DOUBLES MEN | Sunday": 25,
            "CHARITY | HYROX DOUBLES WOMEN | Sunday": 20
          }
        }
      }
    },
    {
      "date": "2026-04-01",
      "fetched_at": "2026-04-01T20:50:14.491259+02:00",
      "total_stock": 15,
      "data": {
        "tickets": [
          {
            "parkur": "Singles",
            "ticket": "HYROX PRO MEN | Saturday",
            "stock": 16
          },
          {
            "parkur": "Singles",
            "ticket": "CHARITY | HYROX MEN | Saturday",
            "stock": 34
          },
          {
            "parkur": "Singles",
            "ticket": "CHARITY | HYROX PRO WOMEN | Saturday",
            "stock": 30
          },
          {
            "parkur": "Singles",
            "ticket": "CHARITY | HYROX PRO MEN | Saturday",
            "stock": 29
          },
          {
            "parkur": "Singles",
            "ticket": "HYROX ADAPTIVE MEN | Saturday",
            "stock": 2
          },
          {
            "parkur": "Singles",
            "ticket": "CHARITY | HYROX WOMEN | Sunday",
            "stock": 42
          },
          {
            "parkur": "Singles",
            "ticket": "HYROX ADAPTIVE WOMEN | Sunday",
            "stock": 7
          },
          {
            "parkur": "Doubles",
            "ticket": "HYROX PRO DOUBLES MEN | Saturday",
            "stock": 34
          },
          {
            "parkur": "Doubles",
            "ticket": "CHARITY | HYROX DOUBLES MIXED | Saturday",
            "stock": 11
          },
          {
            "parkur": "Doubles",
            "ticket": "CHARITY | HYROX PRO DOUBLES WOMEN | Saturday",
            "stock": 28
          },
          {
            "parkur": "Doubles",
            "ticket": "CHARITY | HYROX PRO DOUBLES MEN | Saturday",
            "stock": 30
          },
          {
            "parkur": "Doubles",
            "ticket": "CHARITY | HYROX PRO DOUBLES MEN ATHLETE 2 | Saturday",
            "stock": 30
          },
          {
            "parkur": "Doubles",
            "ticket": "HYROX DOUBLES MEN | Sunday",
            "stock": 123
          },
          {
            "parkur": "Doubles",
            "ticket": "CHARITY | HYROX DOUBLES MEN | Sunday",
            "stock": 25
          },
          {
            "parkur": "Doubles",
            "ticket": "CHARITY | HYROX DOUBLES WOMEN | Sunday",
            "stock": 19
          }
        ],
        "by_parkur": {
          "Singles": {
            "HYROX PRO MEN | Saturday": 16,
            "CHARITY | HYROX MEN | Saturday": 34,
            "CHARITY | HYROX PRO WOMEN | Saturday": 30,
            "CHARITY | HYROX PRO MEN | Saturday": 29,
            "HYROX ADAPTIVE MEN | Saturday": 2,
            "CHARITY | HYROX WOMEN | Sunday": 42,
            "HYROX ADAPTIVE WOMEN | Sunday": 7
          },
          "Doubles": {
            "HYROX PRO DOUBLES MEN | Saturday": 34,
            "CHARITY | HYROX DOUBLES MIXED | Saturday": 11,
            "CHARITY | HYROX PRO DOUBLES WOMEN | Saturday": 28,
            "CHARITY | HYROX PRO DOUBLES MEN | Saturday": 30,
            "CHARITY | HYROX PRO DOUBLES MEN ATHLETE 2 | Saturday": 30,
            "HYROX DOUBLES MEN | Sunday": 123,
            "CHARITY | HYROX DOUBLES MEN | Sunday": 25,
            "CHARITY | HYROX DOUBLES WOMEN | Sunday": 19
          }
        }
      }
    },
    {
      "date": "2026-04-02",
      "fetched_at": "2026-04-02T20:44:39.197469+02:00",
      "total_stock": 15,
      "data": {
        "tickets": [
          {
            "parkur": "Singles",
            "ticket": "HYROX PRO MEN | Saturday",
            "stock": 9
          },
          {
            "parkur": "Singles",
            "ticket": "CHARITY | HYROX MEN | Saturday",
            "stock": 33
          },
          {
            "parkur": "Singles",
            "ticket": "CHARITY | HYROX PRO WOMEN | Saturday",
            "stock": 30
          },
          {
            "parkur": "Singles",
            "ticket": "CHARITY | HYROX PRO MEN | Saturday",
            "stock": 29
          },
          {
            "parkur": "Singles",
            "ticket": "HYROX ADAPTIVE MEN | Saturday",
            "stock": 2
          },
          {
            "parkur": "Singles",
            "ticket": "CHARITY | HYROX WOMEN | Sunday",
            "stock": 42
          },
          {
            "parkur": "Singles",
            "ticket": "HYROX ADAPTIVE WOMEN | Sunday",
            "stock": 7
          },
          {
            "parkur": "Doubles",
            "ticket": "HYROX PRO DOUBLES MEN | Saturday",
            "stock": 30
          },
          {
            "parkur": "Doubles",
            "ticket": "CHARITY | HYROX DOUBLES MIXED | Saturday",
            "stock": 10
          },
          {
            "parkur": "Doubles",
            "ticket": "CHARITY | HYROX PRO DOUBLES WOMEN | Saturday",
            "stock": 28
          },
          {
            "parkur": "Doubles",
            "ticket": "CHARITY | HYROX PRO DOUBLES MEN | Saturday",
            "stock": 30
          },
          {
            "parkur": "Doubles",
            "ticket": "CHARITY | HYROX PRO DOUBLES MEN ATHLETE 2 | Saturday",
            "stock": 30
          },
          {
            "parkur": "Doubles",
            "ticket": "HYROX DOUBLES MEN | Sunday",
            "stock": 116
          },
          {
            "parkur": "Doubles",
            "ticket": "CHARITY | HYROX DOUBLES MEN | Sunday",
            "stock": 25
          },
          {
            "parkur": "Doubles",
            "ticket": "CHARITY | HYROX DOUBLES WOMEN | Sunday",
            "stock": 18
          }
        ],
        "by_parkur": {
          "Singles": {
            "HYROX PRO MEN | Saturday": 9,
            "CHARITY | HYROX MEN | Saturday": 33,
            "CHARITY | HYROX PRO WOMEN | Saturday": 30,
            "CHARITY | HYROX PRO MEN | Saturday": 29,
            "HYROX ADAPTIVE MEN | Saturday": 2,
            "CHARITY | HYROX WOMEN | Sunday": 42,
            "HYROX ADAPTIVE WOMEN | Sunday": 7
          },
          "Doubles": {
            "HYROX PRO DOUBLES MEN | Saturday": 30,
            "CHARITY | HYROX DOUBLES MIXED | Saturday": 10,
            "CHARITY | HYROX PRO DOUBLES WOMEN | Saturday": 28,
            "CHARITY | HYROX PRO DOUBLES MEN | Saturday": 30,
            "CHARITY | HYROX PRO DOUBLES MEN ATHLETE 2 | Saturday": 30,
            "HYROX DOUBLES MEN | Sunday": 116,
            "CHARITY | HYROX DOUBLES MEN | Sunday": 25,
            "CHARITY | HYROX DOUBLES WOMEN | Sunday": 18
          }
        }
      }
    },
    {
      "date": "2026-04-03",
      "fetched_at": "2026-04-03T20:36:28.331390+02:00",
      "total_stock": 15,
      "data": {
        "tickets": [
          {
            "parkur": "Singles",
            "ticket": "HYROX PRO MEN | Saturday",
            "stock": 7
          },
          {
            "parkur": "Singles",
            "ticket": "CHARITY | HYROX MEN | Saturday",
            "stock": 32
          },
          {
            "parkur": "Singles",
            "ticket": "CHARITY | HYROX PRO WOMEN | Saturday",
            "stock": 29
          },
          {
            "parkur": "Singles",
            "ticket": "CHARITY | HYROX PRO MEN | Saturday",
            "stock": 29
          },
          {
            "parkur": "Singles",
            "ticket": "HYROX ADAPTIVE MEN | Saturday",
            "stock": 2
          },
          {
            "parkur": "Singles",
            "ticket": "CHARITY | HYROX WOMEN | Sunday",
            "stock": 42
          },
          {
            "parkur": "Singles",
            "ticket": "HYROX ADAPTIVE WOMEN | Sunday",
            "stock": 7
          },
          {
            "parkur": "Doubles",
            "ticket": "HYROX PRO DOUBLES MEN | Saturday",
            "stock": 28
          },
          {
            "parkur": "Doubles",
            "ticket": "CHARITY | HYROX DOUBLES MIXED | Saturday",
            "stock": 9
          },
          {
            "parkur": "Doubles",
            "ticket": "CHARITY | HYROX PRO DOUBLES WOMEN | Saturday",
            "stock": 28
          },
          {
            "parkur": "Doubles",
            "ticket": "CHARITY | HYROX PRO DOUBLES MEN | Saturday",
            "stock": 30
          },
          {
            "parkur": "Doubles",
            "ticket": "CHARITY | HYROX PRO DOUBLES MEN ATHLETE 2 | Saturday",
            "stock": 30
          },
          {
            "parkur": "Doubles",
            "ticket": "HYROX DOUBLES MEN | Sunday",
            "stock": 109
          },
          {
            "parkur": "Doubles",
            "ticket": "CHARITY | HYROX DOUBLES MEN | Sunday",
            "stock": 25
          },
          {
            "parkur": "Doubles",
            "ticket": "CHARITY | HYROX DOUBLES WOMEN | Sunday",
            "stock": 17
          }
        ],
        "by_parkur": {
          "Singles": {
            "HYROX PRO MEN | Saturday": 7,
            "CHARITY | HYROX MEN | Saturday": 32,
            "CHARITY | HYROX PRO WOMEN | Saturday": 29,
            "CHARITY | HYROX PRO MEN | Saturday": 29,
            "HYROX ADAPTIVE MEN | Saturday": 2,
            "CHARITY | HYROX WOMEN | Sunday": 42,
            "HYROX ADAPTIVE WOMEN | Sunday": 7
          },
          "Doubles": {
            "HYROX PRO DOUBLES MEN | Saturday": 28,
            "CHARITY | HYROX DOUBLES MIXED | Saturday": 9,
            "CHARITY | HYROX PRO DOUBLES WOMEN | Saturday": 28,
            "CHARITY | HYROX PRO DOUBLES MEN | Saturday": 30,
            "CHARITY | HYROX PRO DOUBLES MEN ATHLETE 2 | Saturday": 30,
            "HYROX DOUBLES MEN | Sunday": 109,
            "CHARITY | HYROX DOUBLES MEN | Sunday": 25,
            "CHARITY | HYROX DOUBLES WOMEN | Sunday": 17
          }
        }
      }
    },
    {
      "date": "2026-04-04",
      "fetched_at": "2026-04-04T20:30:03.302003+02:00",
      "total_stock": 15,
      "data": {
        "tickets": [
          {
            "parkur": "Singles",
            "ticket": "HYROX PRO MEN | Saturday",
            "stock": 3
          },
          {
            "parkur": "Singles",
            "ticket": "CHARITY | HYROX MEN | Saturday",
            "stock": 32
          },
          {
            "parkur": "Singles",
            "ticket": "CHARITY | HYROX PRO WOMEN | Saturday",
            "stock": 29
          },
          {
            "parkur": "Singles",
            "ticket": "CHARITY | HYROX PRO MEN | Saturday",
            "stock": 29
          },
          {
            "parkur": "Singles",
            "ticket": "HYROX ADAPTIVE MEN | Saturday",
            "stock": 2
          },
          {
            "parkur": "Singles",
            "ticket": "CHARITY | HYROX WOMEN | Sunday",
            "stock": 40
          },
          {
            "parkur": "Singles",
            "ticket": "HYROX ADAPTIVE WOMEN | Sunday",
            "stock": 7
          },
          {
            "parkur": "Doubles",
            "ticket": "HYROX PRO DOUBLES MEN | Saturday",
            "stock": 24
          },
          {
            "parkur": "Doubles",
            "ticket": "CHARITY | HYROX DOUBLES MIXED | Saturday",
            "stock": 8
          },
          {
            "parkur": "Doubles",
            "ticket": "CHARITY | HYROX PRO DOUBLES WOMEN | Saturday",
            "stock": 28
          },
          {
            "parkur": "Doubles",
            "ticket": "CHARITY | HYROX PRO DOUBLES MEN | Saturday",
            "stock": 30
          },
          {
            "parkur": "Doubles",
            "ticket": "CHARITY | HYROX PRO DOUBLES MEN ATHLETE 2 | Saturday",
            "stock": 30
          },
          {
            "parkur": "Doubles",
            "ticket": "HYROX DOUBLES MEN | Sunday",
            "stock": 99
          },
          {
            "parkur": "Doubles",
            "ticket": "CHARITY | HYROX DOUBLES MEN | Sunday",
            "stock": 25
          },
          {
            "parkur": "Doubles",
            "ticket": "CHARITY | HYROX DOUBLES WOMEN | Sunday",
            "stock": 16
          }
        ],
        "by_parkur": {
          "Singles": {
            "HYROX PRO MEN | Saturday": 3,
            "CHARITY | HYROX MEN | Saturday": 32,
            "CHARITY | HYROX PRO WOMEN | Saturday": 29,
            "CHARITY | HYROX PRO MEN | Saturday": 29,
            "HYROX ADAPTIVE MEN | Saturday": 2,
            "CHARITY | HYROX WOMEN | Sunday": 40,
            "HYROX ADAPTIVE WOMEN | Sunday": 7
          },
          "Doubles": {
            "HYROX PRO DOUBLES MEN | Saturday": 24,
            "CHARITY | HYROX DOUBLES MIXED | Saturday": 8,
            "CHARITY | HYROX PRO DOUBLES WOMEN | Saturday": 28,
            "CHARITY | HYROX PRO DOUBLES MEN | Saturday": 30,
            "CHARITY | HYROX PRO DOUBLES MEN ATHLETE 2 | Saturday": 30,
            "HYROX DOUBLES MEN | Sunday": 99,
            "CHARITY | HYROX DOUBLES MEN | Sunday": 25,
            "CHARITY | HYROX DOUBLES WOMEN | Sunday": 16
          }
        }
      }
    },
    {
      "date": "2026-04-05",
      "fetched_at": "2026-04-05T20:31:45.190357+02:00",
      "total_stock": 14,
      "data": {
        "tickets": [
          {
            "parkur": "Singles",
            "ticket": "CHARITY | HYROX MEN | Saturday",
            "stock": 30
          },
          {
            "parkur": "Singles",
            "ticket": "CHARITY | HYROX PRO WOMEN | Saturday",
            "stock": 29
          },
          {
            "parkur": "Singles",
            "ticket": "CHARITY | HYROX PRO MEN | Saturday",
            "stock": 29
          },
          {
            "parkur": "Singles",
            "ticket": "HYROX ADAPTIVE MEN | Saturday",
            "stock": 2
          },
          {
            "parkur": "Singles",
            "ticket": "CHARITY | HYROX WOMEN | Sunday",
            "stock": 39
          },
          {
            "parkur": "Singles",
            "ticket": "HYROX ADAPTIVE WOMEN | Sunday",
            "stock": 8
          },
          {
            "parkur": "Doubles",
            "ticket": "HYROX PRO DOUBLES MEN | Saturday",
            "stock": 24
          },
          {
            "parkur": "Doubles",
            "ticket": "CHARITY | HYROX DOUBLES MIXED | Saturday",
            "stock": 7
          },
          {
            "parkur": "Doubles",
            "ticket": "CHARITY | HYROX PRO DOUBLES WOMEN | Saturday",
            "stock": 28
          },
          {
            "parkur": "Doubles",
            "ticket": "CHARITY | HYROX PRO DOUBLES MEN | Saturday",
            "stock": 30
          },
          {
            "parkur": "Doubles",
            "ticket": "CHARITY | HYROX PRO DOUBLES MEN ATHLETE 2 | Saturday",
            "stock": 30
          },
          {
            "parkur": "Doubles",
            "ticket": "HYROX DOUBLES MEN | Sunday",
            "stock": 89
          },
          {
            "parkur": "Doubles",
            "ticket": "CHARITY | HYROX DOUBLES MEN | Sunday",
            "stock": 25
          },
          {
            "parkur": "Doubles",
            "ticket": "CHARITY | HYROX DOUBLES WOMEN | Sunday",
            "stock": 16
          }
        ],
        "by_parkur": {
          "Singles": {
            "CHARITY | HYROX MEN | Saturday": 30,
            "CHARITY | HYROX PRO WOMEN | Saturday": 29,
            "CHARITY | HYROX PRO MEN | Saturday": 29,
            "HYROX ADAPTIVE MEN | Saturday": 2,
            "CHARITY | HYROX WOMEN | Sunday": 39,
            "HYROX ADAPTIVE WOMEN | Sunday": 8
          },
          "Doubles": {
            "HYROX PRO DOUBLES MEN | Saturday": 24,
            "CHARITY | HYROX DOUBLES MIXED | Saturday": 7,
            "CHARITY | HYROX PRO DOUBLES WOMEN | Saturday": 28,
            "CHARITY | HYROX PRO DOUBLES MEN | Saturday": 30,
            "CHARITY | HYROX PRO DOUBLES MEN ATHLETE 2 | Saturday": 30,
            "HYROX DOUBLES MEN | Sunday": 89,
            "CHARITY | HYROX DOUBLES MEN | Sunday": 25,
            "CHARITY | HYROX DOUBLES WOMEN | Sunday": 16
          }
        }
      }
    },
    {
      "date": "2026-04-06",
      "fetched_at": "2026-04-06T20:45:25.939605+02:00",
      "total_stock": 14,
      "data": {
        "tickets": [
          {
            "parkur": "Singles",
            "ticket": "CHARITY | HYROX MEN | Saturday",
            "stock": 28
          },
          {
            "parkur": "Singles",
            "ticket": "CHARITY | HYROX PRO WOMEN | Saturday",
            "stock": 29
          },
          {
            "parkur": "Singles",
            "ticket": "CHARITY | HYROX PRO MEN | Saturday",
            "stock": 29
          },
          {
            "parkur": "Singles",
            "ticket": "HYROX ADAPTIVE MEN | Saturday",
            "stock": 2
          },
          {
            "parkur": "Singles",
            "ticket": "CHARITY | HYROX WOMEN | Sunday",
            "stock": 39
          },
          {
            "parkur": "Singles",
            "ticket": "HYROX ADAPTIVE WOMEN | Sunday",
            "stock": 8
          },
          {
            "parkur": "Doubles",
            "ticket": "HYROX PRO DOUBLES MEN | Saturday",
            "stock": 23
          },
          {
            "parkur": "Doubles",
            "ticket": "CHARITY | HYROX DOUBLES MIXED | Saturday",
            "stock": 7
          },
          {
            "parkur": "Doubles",
            "ticket": "CHARITY | HYROX PRO DOUBLES WOMEN | Saturday",
            "stock": 28
          },
          {
            "parkur": "Doubles",
            "ticket": "CHARITY | HYROX PRO DOUBLES MEN | Saturday",
            "stock": 30
          },
          {
            "parkur": "Doubles",
            "ticket": "CHARITY | HYROX PRO DOUBLES MEN ATHLETE 2 | Saturday",
            "stock": 30
          },
          {
            "parkur": "Doubles",
            "ticket": "HYROX DOUBLES MEN | Sunday",
            "stock": 79
          },
          {
            "parkur": "Doubles",
            "ticket": "CHARITY | HYROX DOUBLES MEN | Sunday",
            "stock": 25
          },
          {
            "parkur": "Doubles",
            "ticket": "CHARITY | HYROX DOUBLES WOMEN | Sunday",
            "stock": 16
          }
        ],
        "by_parkur": {
          "Singles": {
            "CHARITY | HYROX MEN | Saturday": 28,
            "CHARITY | HYROX PRO WOMEN | Saturday": 29,
            "CHARITY | HYROX PRO MEN | Saturday": 29,
            "HYROX ADAPTIVE MEN | Saturday": 2,
            "CHARITY | HYROX WOMEN | Sunday": 39,
            "HYROX ADAPTIVE WOMEN | Sunday": 8
          },
          "Doubles": {
            "HYROX PRO DOUBLES MEN | Saturday": 23,
            "CHARITY | HYROX DOUBLES MIXED | Saturday": 7,
            "CHARITY | HYROX PRO DOUBLES WOMEN | Saturday": 28,
            "CHARITY | HYROX PRO DOUBLES MEN | Saturday": 30,
            "CHARITY | HYROX PRO DOUBLES MEN ATHLETE 2 | Saturday": 30,
            "HYROX DOUBLES MEN | Sunday": 79,
            "CHARITY | HYROX DOUBLES MEN | Sunday": 25,
            "CHARITY | HYROX DOUBLES WOMEN | Sunday": 16
          }
        }
      }
    },
    {
      "date": "2026-04-07",
      "fetched_at": "2026-04-07T20:52:11.403932+02:00",
      "total_stock": 14,
      "data": {
        "tickets": [
          {
            "parkur": "Singles",
            "ticket": "CHARITY | HYROX MEN | Saturday",
            "stock": 28
          },
          {
            "parkur": "Singles",
            "ticket": "CHARITY | HYROX PRO WOMEN | Saturday",
            "stock": 29
          },
          {
            "parkur": "Singles",
            "ticket": "CHARITY | HYROX PRO MEN | Saturday",
            "stock": 29
          },
          {
            "parkur": "Singles",
            "ticket": "HYROX ADAPTIVE MEN | Saturday",
            "stock": 2
          },
          {
            "parkur": "Singles",
            "ticket": "CHARITY | HYROX WOMEN | Sunday",
            "stock": 37
          },
          {
            "parkur": "Singles",
            "ticket": "HYROX ADAPTIVE WOMEN | Sunday",
            "stock": 8
          },
          {
            "parkur": "Doubles",
            "ticket": "HYROX PRO DOUBLES MEN | Saturday",
            "stock": 21
          },
          {
            "parkur": "Doubles",
            "ticket": "CHARITY | HYROX DOUBLES MIXED | Saturday",
            "stock": 6
          },
          {
            "parkur": "Doubles",
            "ticket": "CHARITY | HYROX PRO DOUBLES WOMEN | Saturday",
            "stock": 28
          },
          {
            "parkur": "Doubles",
            "ticket": "CHARITY | HYROX PRO DOUBLES MEN | Saturday",
            "stock": 30
          },
          {
            "parkur": "Doubles",
            "ticket": "CHARITY | HYROX PRO DOUBLES MEN ATHLETE 2 | Saturday",
            "stock": 30
          },
          {
            "parkur": "Doubles",
            "ticket": "HYROX DOUBLES MEN | Sunday",
            "stock": 72
          },
          {
            "parkur": "Doubles",
            "ticket": "CHARITY | HYROX DOUBLES MEN | Sunday",
            "stock": 25
          },
          {
            "parkur": "Doubles",
            "ticket": "CHARITY | HYROX DOUBLES WOMEN | Sunday",
            "stock": 15
          }
        ],
        "by_parkur": {
          "Singles": {
            "CHARITY | HYROX MEN | Saturday": 28,
            "CHARITY | HYROX PRO WOMEN | Saturday": 29,
            "CHARITY | HYROX PRO MEN | Saturday": 29,
            "HYROX ADAPTIVE MEN | Saturday": 2,
            "CHARITY | HYROX WOMEN | Sunday": 37,
            "HYROX ADAPTIVE WOMEN | Sunday": 8
          },
          "Doubles": {
            "HYROX PRO DOUBLES MEN | Saturday": 21,
            "CHARITY | HYROX DOUBLES MIXED | Saturday": 6,
            "CHARITY | HYROX PRO DOUBLES WOMEN | Saturday": 28,
            "CHARITY | HYROX PRO DOUBLES MEN | Saturday": 30,
            "CHARITY | HYROX PRO DOUBLES MEN ATHLETE 2 | Saturday": 30,
            "HYROX DOUBLES MEN | Sunday": 72,
            "CHARITY | HYROX DOUBLES MEN | Sunday": 25,
            "CHARITY | HYROX DOUBLES WOMEN | Sunday": 15
          }
        }
      }
    },
    {
      "date": "2026-04-08",
      "fetched_at": "2026-04-08T10:08:06.690937+02:00",
      "total_stock": 14,
      "data": {
        "tickets": [
          {
            "parkur": "Singles",
            "ticket": "CHARITY | HYROX MEN | Saturday",
            "stock": 28
          },
          {
            "parkur": "Singles",
            "ticket": "CHARITY | HYROX PRO WOMEN | Saturday",
            "stock": 29
          },
          {
            "parkur": "Singles",
            "ticket": "CHARITY | HYROX PRO MEN | Saturday",
            "stock": 29
          },
          {
            "parkur": "Singles",
            "ticket": "HYROX ADAPTIVE MEN | Saturday",
            "stock": 2
          },
          {
            "parkur": "Singles",
            "ticket": "CHARITY | HYROX WOMEN | Sunday",
            "stock": 36
          },
          {
            "parkur": "Singles",
            "ticket": "HYROX ADAPTIVE WOMEN | Sunday",
            "stock": 8
          },
          {
            "parkur": "Doubles",
            "ticket": "HYROX PRO DOUBLES MEN | Saturday",
            "stock": 21
          },
          {
            "parkur": "Doubles",
            "ticket": "CHARITY | HYROX DOUBLES MIXED | Saturday",
            "stock": 6
          },
          {
            "parkur": "Doubles",
            "ticket": "CHARITY | HYROX PRO DOUBLES WOMEN | Saturday",
            "stock": 28
          },
          {
            "parkur": "Doubles",
            "ticket": "CHARITY | HYROX PRO DOUBLES MEN | Saturday",
            "stock": 30
          },
          {
            "parkur": "Doubles",
            "ticket": "CHARITY | HYROX PRO DOUBLES MEN ATHLETE 2 | Saturday",
            "stock": 30
          },
          {
            "parkur": "Doubles",
            "ticket": "HYROX DOUBLES MEN | Sunday",
            "stock": 69
          },
          {
            "parkur": "Doubles",
            "ticket": "CHARITY | HYROX DOUBLES MEN | Sunday",
            "stock": 25
          },
          {
            "parkur": "Doubles",
            "ticket": "CHARITY | HYROX DOUBLES WOMEN | Sunday",
            "stock": 15
          }
        ],
        "by_parkur": {
          "Singles": {
            "CHARITY | HYROX MEN | Saturday": 28,
            "CHARITY | HYROX PRO WOMEN | Saturday": 29,
            "CHARITY | HYROX PRO MEN | Saturday": 29,
            "HYROX ADAPTIVE MEN | Saturday": 2,
            "CHARITY | HYROX WOMEN | Sunday": 36,
            "HYROX ADAPTIVE WOMEN | Sunday": 8
          },
          "Doubles": {
            "HYROX PRO DOUBLES MEN | Saturday": 21,
            "CHARITY | HYROX DOUBLES MIXED | Saturday": 6,
            "CHARITY | HYROX PRO DOUBLES WOMEN | Saturday": 28,
            "CHARITY | HYROX PRO DOUBLES MEN | Saturday": 30,
            "CHARITY | HYROX PRO DOUBLES MEN ATHLETE 2 | Saturday": 30,
            "HYROX DOUBLES MEN | Sunday": 69,
            "CHARITY | HYROX DOUBLES MEN | Sunday": 25,
            "CHARITY | HYROX DOUBLES WOMEN | Sunday": 15
          }
        }
      }
    }
  ]
}